{
  "ComponentIndexes": {},
  "ControlUniqueGuids": {},
  "ControlUniqueIds": {
    "App": 1,
    "Assigned_to": 25,
    "Button1": 11,
    "Button2": 8,
    "Button3": 12,
    "Category": 20,
    "Container1": 5,
    "DataTable1": 17,
    "Description_1": 19,
    "Dropdown_Priority": 15,
    "Dropdown_Progress": 16,
    "Due_Date": 24,
    "GalleryData": 26,
    "galleryTemplate4": 27,
    "Group1": 40,
    "Host": 3,
    "Icon1": 6,
    "Icon1_1": 14,
    "Label1": 7,
    "Label2": 39,
    "Label3": 9,
    "Label3_1": 10,
    "Priority_1": 22,
    "Progress_1": 21,
    "Rectangle1": 28,
    "Screen1": 4,
    "Separator1": 37,
    "Slider1": 38,
    "Start_Date": 23,
    "Subtitle2": 32,
    "Subtitle2_1": 33,
    "Subtitle2_2": 30,
    "Subtitle2_3": 31,
    "Subtitle2_4": 34,
    "Subtitle2_5": 35,
    "Subtitle2_6": 36,
    "Title_1": 18,
    "Title3": 29,
    "txtSearch": 13
  },
  "DataTableCustomControlTemplateJsons": {
    "Assigned_to": "{\"name\":\"dataColumn\",\"version\":\"1.1\",\"properties\":[{\"name\":\"AutoWidth\",\"hidden\":false,\"type\":\"boolean\",\"category\":\"data\",\"displayName\":\"Can grow\",\"direction\":\"inout\",\"useForProjection\":false,\"defaultValue\":\"true\"},{\"name\":\"DisplayName\",\"hidden\":false,\"type\":\"string\",\"category\":\"data\",\"displayName\":\"Text\",\"direction\":\"inout\",\"useForProjection\":false,\"defaultValue\":\"\"},{\"name\":\"IsHyperlink\",\"hidden\":false,\"type\":\"boolean\",\"category\":\"data\",\"displayName\":\"Is hyperlink\",\"direction\":\"inout\",\"useForProjection\":false,\"defaultValue\":\"false\"},{\"name\":\"OnSelect\",\"hidden\":false,\"type\":\"boolean\",\"category\":\"behavior\",\"displayName\":\"On select\",\"direction\":\"in\",\"useForProjection\":false,\"defaultValue\":\"false\"},{\"name\":\"Width\",\"hidden\":false},{\"name\":\"Height\",\"hidden\":true},{\"name\":\"X\",\"hidden\":true},{\"name\":\"Y\",\"hidden\":true},{\"name\":\"Type\",\"hidden\":true,\"type\":\"string\",\"category\":\"data\",\"displayName\":\"Type\",\"direction\":\"inout\",\"useForProjection\":false,\"defaultValue\":\"\"},{\"name\":\"FieldName\",\"hidden\":true,\"type\":\"string\",\"category\":\"data\",\"displayName\":\"Field name\",\"direction\":\"inout\",\"useForProjection\":true,\"defaultValue\":\"\"},{\"name\":\"Required\",\"hidden\":true,\"type\":\"boolean\",\"category\":\"data\",\"displayName\":\"Required\",\"direction\":\"inout\",\"useForProjection\":false,\"defaultValue\":\"false\"},{\"name\":\"TitleProperty\",\"hidden\":true,\"type\":\"string\",\"category\":\"data\",\"displayName\":\"Title\",\"direction\":\"inout\",\"useForProjection\":false,\"defaultValue\":\"\"},{\"name\":\"Order\",\"hidden\":true,\"type\":\"number\",\"category\":\"data\",\"displayName\":\"Order\",\"direction\":\"inout\",\"useForProjection\":false,\"defaultValue\":\"-1\"},{\"name\":\"VariantName\",\"hidden\":true,\"type\":\"string\",\"category\":\"data\",\"displayName\":\"Variant name\",\"direction\":\"inout\",\"useForProjection\":false,\"defaultValue\":\"\"}],\"docVersion\":\"1.342\"}",
    "Category": "{\"name\":\"dataColumn\",\"version\":\"1.1\",\"properties\":[{\"name\":\"AutoWidth\",\"hidden\":false,\"type\":\"boolean\",\"category\":\"data\",\"displayName\":\"Can grow\",\"direction\":\"inout\",\"useForProjection\":false,\"defaultValue\":\"true\"},{\"name\":\"DisplayName\",\"hidden\":false,\"type\":\"string\",\"category\":\"data\",\"displayName\":\"Text\",\"direction\":\"inout\",\"useForProjection\":false,\"defaultValue\":\"\"},{\"name\":\"IsHyperlink\",\"hidden\":false,\"type\":\"boolean\",\"category\":\"data\",\"displayName\":\"Is hyperlink\",\"direction\":\"inout\",\"useForProjection\":false,\"defaultValue\":\"false\"},{\"name\":\"OnSelect\",\"hidden\":false,\"type\":\"boolean\",\"category\":\"behavior\",\"displayName\":\"On select\",\"direction\":\"in\",\"useForProjection\":false,\"defaultValue\":\"false\"},{\"name\":\"Width\",\"hidden\":false},{\"name\":\"Height\",\"hidden\":true},{\"name\":\"X\",\"hidden\":true},{\"name\":\"Y\",\"hidden\":true},{\"name\":\"Type\",\"hidden\":true,\"type\":\"string\",\"category\":\"data\",\"displayName\":\"Type\",\"direction\":\"inout\",\"useForProjection\":false,\"defaultValue\":\"\"},{\"name\":\"FieldName\",\"hidden\":true,\"type\":\"string\",\"category\":\"data\",\"displayName\":\"Field name\",\"direction\":\"inout\",\"useForProjection\":true,\"defaultValue\":\"\"},{\"name\":\"Required\",\"hidden\":true,\"type\":\"boolean\",\"category\":\"data\",\"displayName\":\"Required\",\"direction\":\"inout\",\"useForProjection\":false,\"defaultValue\":\"false\"},{\"name\":\"TitleProperty\",\"hidden\":true,\"type\":\"string\",\"category\":\"data\",\"displayName\":\"Title\",\"direction\":\"inout\",\"useForProjection\":false,\"defaultValue\":\"\"},{\"name\":\"Order\",\"hidden\":true,\"type\":\"number\",\"category\":\"data\",\"displayName\":\"Order\",\"direction\":\"inout\",\"useForProjection\":false,\"defaultValue\":\"-1\"},{\"name\":\"VariantName\",\"hidden\":true,\"type\":\"string\",\"category\":\"data\",\"displayName\":\"Variant name\",\"direction\":\"inout\",\"useForProjection\":false,\"defaultValue\":\"\"}],\"docVersion\":\"1.342\"}",
    "Description_1": "{\"name\":\"dataColumn\",\"version\":\"1.1\",\"properties\":[{\"name\":\"AutoWidth\",\"hidden\":false,\"type\":\"boolean\",\"category\":\"data\",\"displayName\":\"Can grow\",\"direction\":\"inout\",\"useForProjection\":false,\"defaultValue\":\"true\"},{\"name\":\"DisplayName\",\"hidden\":false,\"type\":\"string\",\"category\":\"data\",\"displayName\":\"Text\",\"direction\":\"inout\",\"useForProjection\":false,\"defaultValue\":\"\"},{\"name\":\"IsHyperlink\",\"hidden\":false,\"type\":\"boolean\",\"category\":\"data\",\"displayName\":\"Is hyperlink\",\"direction\":\"inout\",\"useForProjection\":false,\"defaultValue\":\"false\"},{\"name\":\"OnSelect\",\"hidden\":false,\"type\":\"boolean\",\"category\":\"behavior\",\"displayName\":\"On select\",\"direction\":\"in\",\"useForProjection\":false,\"defaultValue\":\"false\"},{\"name\":\"Width\",\"hidden\":false},{\"name\":\"Height\",\"hidden\":true},{\"name\":\"X\",\"hidden\":true},{\"name\":\"Y\",\"hidden\":true},{\"name\":\"Type\",\"hidden\":true,\"type\":\"string\",\"category\":\"data\",\"displayName\":\"Type\",\"direction\":\"inout\",\"useForProjection\":false,\"defaultValue\":\"\"},{\"name\":\"FieldName\",\"hidden\":true,\"type\":\"string\",\"category\":\"data\",\"displayName\":\"Field name\",\"direction\":\"inout\",\"useForProjection\":true,\"defaultValue\":\"\"},{\"name\":\"Required\",\"hidden\":true,\"type\":\"boolean\",\"category\":\"data\",\"displayName\":\"Required\",\"direction\":\"inout\",\"useForProjection\":false,\"defaultValue\":\"false\"},{\"name\":\"TitleProperty\",\"hidden\":true,\"type\":\"string\",\"category\":\"data\",\"displayName\":\"Title\",\"direction\":\"inout\",\"useForProjection\":false,\"defaultValue\":\"\"},{\"name\":\"Order\",\"hidden\":true,\"type\":\"number\",\"category\":\"data\",\"displayName\":\"Order\",\"direction\":\"inout\",\"useForProjection\":false,\"defaultValue\":\"-1\"},{\"name\":\"VariantName\",\"hidden\":true,\"type\":\"string\",\"category\":\"data\",\"displayName\":\"Variant name\",\"direction\":\"inout\",\"useForProjection\":false,\"defaultValue\":\"\"}],\"docVersion\":\"1.342\"}",
    "Due_Date": "{\"name\":\"dataColumn\",\"version\":\"1.1\",\"properties\":[{\"name\":\"AutoWidth\",\"hidden\":false,\"type\":\"boolean\",\"category\":\"data\",\"displayName\":\"Can grow\",\"direction\":\"inout\",\"useForProjection\":false,\"defaultValue\":\"true\"},{\"name\":\"DisplayName\",\"hidden\":false,\"type\":\"string\",\"category\":\"data\",\"displayName\":\"Text\",\"direction\":\"inout\",\"useForProjection\":false,\"defaultValue\":\"\"},{\"name\":\"IsHyperlink\",\"hidden\":false,\"type\":\"boolean\",\"category\":\"data\",\"displayName\":\"Is hyperlink\",\"direction\":\"inout\",\"useForProjection\":false,\"defaultValue\":\"false\"},{\"name\":\"OnSelect\",\"hidden\":false,\"type\":\"boolean\",\"category\":\"behavior\",\"displayName\":\"On select\",\"direction\":\"in\",\"useForProjection\":false,\"defaultValue\":\"false\"},{\"name\":\"Width\",\"hidden\":false},{\"name\":\"Height\",\"hidden\":true},{\"name\":\"X\",\"hidden\":true},{\"name\":\"Y\",\"hidden\":true},{\"name\":\"Type\",\"hidden\":true,\"type\":\"string\",\"category\":\"data\",\"displayName\":\"Type\",\"direction\":\"inout\",\"useForProjection\":false,\"defaultValue\":\"\"},{\"name\":\"FieldName\",\"hidden\":true,\"type\":\"string\",\"category\":\"data\",\"displayName\":\"Field name\",\"direction\":\"inout\",\"useForProjection\":true,\"defaultValue\":\"\"},{\"name\":\"Required\",\"hidden\":true,\"type\":\"boolean\",\"category\":\"data\",\"displayName\":\"Required\",\"direction\":\"inout\",\"useForProjection\":false,\"defaultValue\":\"false\"},{\"name\":\"TitleProperty\",\"hidden\":true,\"type\":\"string\",\"category\":\"data\",\"displayName\":\"Title\",\"direction\":\"inout\",\"useForProjection\":false,\"defaultValue\":\"\"},{\"name\":\"Order\",\"hidden\":true,\"type\":\"number\",\"category\":\"data\",\"displayName\":\"Order\",\"direction\":\"inout\",\"useForProjection\":false,\"defaultValue\":\"-1\"},{\"name\":\"VariantName\",\"hidden\":true,\"type\":\"string\",\"category\":\"data\",\"displayName\":\"Variant name\",\"direction\":\"inout\",\"useForProjection\":false,\"defaultValue\":\"\"}],\"docVersion\":\"1.342\"}",
    "Priority_1": "{\"name\":\"dataColumn\",\"version\":\"1.1\",\"properties\":[{\"name\":\"AutoWidth\",\"hidden\":false,\"type\":\"boolean\",\"category\":\"data\",\"displayName\":\"Can grow\",\"direction\":\"inout\",\"useForProjection\":false,\"defaultValue\":\"true\"},{\"name\":\"DisplayName\",\"hidden\":false,\"type\":\"string\",\"category\":\"data\",\"displayName\":\"Text\",\"direction\":\"inout\",\"useForProjection\":false,\"defaultValue\":\"\"},{\"name\":\"IsHyperlink\",\"hidden\":false,\"type\":\"boolean\",\"category\":\"data\",\"displayName\":\"Is hyperlink\",\"direction\":\"inout\",\"useForProjection\":false,\"defaultValue\":\"false\"},{\"name\":\"OnSelect\",\"hidden\":false,\"type\":\"boolean\",\"category\":\"behavior\",\"displayName\":\"On select\",\"direction\":\"in\",\"useForProjection\":false,\"defaultValue\":\"false\"},{\"name\":\"Width\",\"hidden\":false},{\"name\":\"Height\",\"hidden\":true},{\"name\":\"X\",\"hidden\":true},{\"name\":\"Y\",\"hidden\":true},{\"name\":\"Type\",\"hidden\":true,\"type\":\"string\",\"category\":\"data\",\"displayName\":\"Type\",\"direction\":\"inout\",\"useForProjection\":false,\"defaultValue\":\"\"},{\"name\":\"FieldName\",\"hidden\":true,\"type\":\"string\",\"category\":\"data\",\"displayName\":\"Field name\",\"direction\":\"inout\",\"useForProjection\":true,\"defaultValue\":\"\"},{\"name\":\"Required\",\"hidden\":true,\"type\":\"boolean\",\"category\":\"data\",\"displayName\":\"Required\",\"direction\":\"inout\",\"useForProjection\":false,\"defaultValue\":\"false\"},{\"name\":\"TitleProperty\",\"hidden\":true,\"type\":\"string\",\"category\":\"data\",\"displayName\":\"Title\",\"direction\":\"inout\",\"useForProjection\":false,\"defaultValue\":\"\"},{\"name\":\"Order\",\"hidden\":true,\"type\":\"number\",\"category\":\"data\",\"displayName\":\"Order\",\"direction\":\"inout\",\"useForProjection\":false,\"defaultValue\":\"-1\"},{\"name\":\"VariantName\",\"hidden\":true,\"type\":\"string\",\"category\":\"data\",\"displayName\":\"Variant name\",\"direction\":\"inout\",\"useForProjection\":false,\"defaultValue\":\"\"}],\"docVersion\":\"1.342\"}",
    "Progress_1": "{\"name\":\"dataColumn\",\"version\":\"1.1\",\"properties\":[{\"name\":\"AutoWidth\",\"hidden\":false,\"type\":\"boolean\",\"category\":\"data\",\"displayName\":\"Can grow\",\"direction\":\"inout\",\"useForProjection\":false,\"defaultValue\":\"true\"},{\"name\":\"DisplayName\",\"hidden\":false,\"type\":\"string\",\"category\":\"data\",\"displayName\":\"Text\",\"direction\":\"inout\",\"useForProjection\":false,\"defaultValue\":\"\"},{\"name\":\"IsHyperlink\",\"hidden\":false,\"type\":\"boolean\",\"category\":\"data\",\"displayName\":\"Is hyperlink\",\"direction\":\"inout\",\"useForProjection\":false,\"defaultValue\":\"false\"},{\"name\":\"OnSelect\",\"hidden\":false,\"type\":\"boolean\",\"category\":\"behavior\",\"displayName\":\"On select\",\"direction\":\"in\",\"useForProjection\":false,\"defaultValue\":\"false\"},{\"name\":\"Width\",\"hidden\":false},{\"name\":\"Height\",\"hidden\":true},{\"name\":\"X\",\"hidden\":true},{\"name\":\"Y\",\"hidden\":true},{\"name\":\"Type\",\"hidden\":true,\"type\":\"string\",\"category\":\"data\",\"displayName\":\"Type\",\"direction\":\"inout\",\"useForProjection\":false,\"defaultValue\":\"\"},{\"name\":\"FieldName\",\"hidden\":true,\"type\":\"string\",\"category\":\"data\",\"displayName\":\"Field name\",\"direction\":\"inout\",\"useForProjection\":true,\"defaultValue\":\"\"},{\"name\":\"Required\",\"hidden\":true,\"type\":\"boolean\",\"category\":\"data\",\"displayName\":\"Required\",\"direction\":\"inout\",\"useForProjection\":false,\"defaultValue\":\"false\"},{\"name\":\"TitleProperty\",\"hidden\":true,\"type\":\"string\",\"category\":\"data\",\"displayName\":\"Title\",\"direction\":\"inout\",\"useForProjection\":false,\"defaultValue\":\"\"},{\"name\":\"Order\",\"hidden\":true,\"type\":\"number\",\"category\":\"data\",\"displayName\":\"Order\",\"direction\":\"inout\",\"useForProjection\":false,\"defaultValue\":\"-1\"},{\"name\":\"VariantName\",\"hidden\":true,\"type\":\"string\",\"category\":\"data\",\"displayName\":\"Variant name\",\"direction\":\"inout\",\"useForProjection\":false,\"defaultValue\":\"\"}],\"docVersion\":\"1.342\"}",
    "Start_Date": "{\"name\":\"dataColumn\",\"version\":\"1.1\",\"properties\":[{\"name\":\"AutoWidth\",\"hidden\":false,\"type\":\"boolean\",\"category\":\"data\",\"displayName\":\"Can grow\",\"direction\":\"inout\",\"useForProjection\":false,\"defaultValue\":\"true\"},{\"name\":\"DisplayName\",\"hidden\":false,\"type\":\"string\",\"category\":\"data\",\"displayName\":\"Text\",\"direction\":\"inout\",\"useForProjection\":false,\"defaultValue\":\"\"},{\"name\":\"IsHyperlink\",\"hidden\":false,\"type\":\"boolean\",\"category\":\"data\",\"displayName\":\"Is hyperlink\",\"direction\":\"inout\",\"useForProjection\":false,\"defaultValue\":\"false\"},{\"name\":\"OnSelect\",\"hidden\":false,\"type\":\"boolean\",\"category\":\"behavior\",\"displayName\":\"On select\",\"direction\":\"in\",\"useForProjection\":false,\"defaultValue\":\"false\"},{\"name\":\"Width\",\"hidden\":false},{\"name\":\"Height\",\"hidden\":true},{\"name\":\"X\",\"hidden\":true},{\"name\":\"Y\",\"hidden\":true},{\"name\":\"Type\",\"hidden\":true,\"type\":\"string\",\"category\":\"data\",\"displayName\":\"Type\",\"direction\":\"inout\",\"useForProjection\":false,\"defaultValue\":\"\"},{\"name\":\"FieldName\",\"hidden\":true,\"type\":\"string\",\"category\":\"data\",\"displayName\":\"Field name\",\"direction\":\"inout\",\"useForProjection\":true,\"defaultValue\":\"\"},{\"name\":\"Required\",\"hidden\":true,\"type\":\"boolean\",\"category\":\"data\",\"displayName\":\"Required\",\"direction\":\"inout\",\"useForProjection\":false,\"defaultValue\":\"false\"},{\"name\":\"TitleProperty\",\"hidden\":true,\"type\":\"string\",\"category\":\"data\",\"displayName\":\"Title\",\"direction\":\"inout\",\"useForProjection\":false,\"defaultValue\":\"\"},{\"name\":\"Order\",\"hidden\":true,\"type\":\"number\",\"category\":\"data\",\"displayName\":\"Order\",\"direction\":\"inout\",\"useForProjection\":false,\"defaultValue\":\"-1\"},{\"name\":\"VariantName\",\"hidden\":true,\"type\":\"string\",\"category\":\"data\",\"displayName\":\"Variant name\",\"direction\":\"inout\",\"useForProjection\":false,\"defaultValue\":\"\"}],\"docVersion\":\"1.342\"}",
    "Title_1": "{\"name\":\"dataColumn\",\"version\":\"1.1\",\"properties\":[{\"name\":\"AutoWidth\",\"hidden\":false,\"type\":\"boolean\",\"category\":\"data\",\"displayName\":\"Can grow\",\"direction\":\"inout\",\"useForProjection\":false,\"defaultValue\":\"true\"},{\"name\":\"DisplayName\",\"hidden\":false,\"type\":\"string\",\"category\":\"data\",\"displayName\":\"Text\",\"direction\":\"inout\",\"useForProjection\":false,\"defaultValue\":\"\"},{\"name\":\"IsHyperlink\",\"hidden\":false,\"type\":\"boolean\",\"category\":\"data\",\"displayName\":\"Is hyperlink\",\"direction\":\"inout\",\"useForProjection\":false,\"defaultValue\":\"false\"},{\"name\":\"OnSelect\",\"hidden\":false,\"type\":\"boolean\",\"category\":\"behavior\",\"displayName\":\"On select\",\"direction\":\"in\",\"useForProjection\":false,\"defaultValue\":\"false\"},{\"name\":\"Width\",\"hidden\":false},{\"name\":\"Height\",\"hidden\":true},{\"name\":\"X\",\"hidden\":true},{\"name\":\"Y\",\"hidden\":true},{\"name\":\"Type\",\"hidden\":true,\"type\":\"string\",\"category\":\"data\",\"displayName\":\"Type\",\"direction\":\"inout\",\"useForProjection\":false,\"defaultValue\":\"\"},{\"name\":\"FieldName\",\"hidden\":true,\"type\":\"string\",\"category\":\"data\",\"displayName\":\"Field name\",\"direction\":\"inout\",\"useForProjection\":true,\"defaultValue\":\"\"},{\"name\":\"Required\",\"hidden\":true,\"type\":\"boolean\",\"category\":\"data\",\"displayName\":\"Required\",\"direction\":\"inout\",\"useForProjection\":false,\"defaultValue\":\"false\"},{\"name\":\"TitleProperty\",\"hidden\":true,\"type\":\"string\",\"category\":\"data\",\"displayName\":\"Title\",\"direction\":\"inout\",\"useForProjection\":false,\"defaultValue\":\"\"},{\"name\":\"Order\",\"hidden\":true,\"type\":\"number\",\"category\":\"data\",\"displayName\":\"Order\",\"direction\":\"inout\",\"useForProjection\":false,\"defaultValue\":\"-1\"},{\"name\":\"VariantName\",\"hidden\":true,\"type\":\"string\",\"category\":\"data\",\"displayName\":\"Variant name\",\"direction\":\"inout\",\"useForProjection\":false,\"defaultValue\":\"\"}],\"docVersion\":\"1.342\"}"
  },
  "FunctionParamsInvariantScripts": {},
  "FunctionParamsInvariantScriptsOnInstances": {},
  "HeaderLastSavedDateTimeUTC": "07/12/2024 09:16:34",
  "IsLegacyComponentAllowGlobalScopeCase": false,
  "LocalConnectionIDReferences": {
    "90b8b3a3-0a27-4ca4-a8b9-cc10afd90e91": "\"/providers/microsoft.powerapps/apis/shared_sharepointonline/connections/38cb66ce397840a0a9db5aabada91e12\""
  },
  "LocalDatabaseReferencesAsEmpty": true,
  "LocalResourceFileNames": {},
  "LocalResourceRootPaths": {},
  "OrderComponentMetadata": {},
  "OrderComponentTemplate": {},
  "OrderDataSource": {
    "CustomGallerySample": 1,
    "DropDownSample": 3,
    "ListboxSample": 2,
    "TBL_WorkProgressTracker3": 0
  },
  "OrderGroupControls": {
    "Group1": {
      "Button1": 1,
      "Icon1_1": 2,
      "txtSearch": 0
    }
  },
  "OrderPcfTemplate": {},
  "OrderTemplate": {},
  "OrderXMLTemplate": {
    "button": 3,
    "dataGrid": 6,
    "dropdown": 5,
    "gallery": 7,
    "groupContainer": 0,
    "icon": 1,
    "label": 2,
    "rectangle": 8,
    "slider": 9,
    "text": 4
  },
  "OverridablePropertiesEntry": {
    "App": {},
    "Assigned_to": {},
    "Button1": {},
    "Button2": {},
    "Button3": {},
    "Category": {},
    "Container1": {},
    "DataTable1": {},
    "Description_1": {},
    "Dropdown_Priority": {},
    "Dropdown_Progress": {},
    "Due_Date": {},
    "GalleryData": {},
    "galleryTemplate4": {},
    "Group1": {},
    "Host": {},
    "Icon1": {},
    "Icon1_1": {},
    "Label1": {},
    "Label2": {},
    "Label3": {},
    "Label3_1": {},
    "Priority_1": {},
    "Progress_1": {},
    "Rectangle1": {},
    "Screen1": {},
    "Separator1": {},
    "Slider1": {},
    "Start_Date": {},
    "Subtitle2": {},
    "Subtitle2_1": {},
    "Subtitle2_2": {},
    "Subtitle2_3": {},
    "Subtitle2_4": {},
    "Subtitle2_5": {},
    "Subtitle2_6": {},
    "Title_1": {},
    "Title3": {},
    "txtSearch": {}
  },
  "PCFDynamicSchemaForIRRetrievalEntry": {},
  "PCFTemplateEntry": {},
  "PublishOrderIndices": {
    "App": 0,
    "Assigned_to": 21,
    "Button1": 6,
    "Button2": 3,
    "Button3": 8,
    "Category": 16,
    "Container1": 0,
    "DataTable1": 13,
    "Description_1": 15,
    "Dropdown_Priority": 11,
    "Dropdown_Progress": 12,
    "Due_Date": 20,
    "GalleryData": 22,
    "galleryTemplate4": 23,
    "Group1": 7,
    "Host": 0,
    "Icon1": 1,
    "Icon1_1": 10,
    "Label1": 2,
    "Label2": 35,
    "Label3": 4,
    "Label3_1": 5,
    "Priority_1": 18,
    "Progress_1": 17,
    "Rectangle1": 24,
    "Screen1": 0,
    "Separator1": 33,
    "Slider1": 34,
    "Start_Date": 19,
    "Subtitle2": 28,
    "Subtitle2_1": 29,
    "Subtitle2_2": 26,
    "Subtitle2_3": 27,
    "Subtitle2_4": 30,
    "Subtitle2_5": 31,
    "Subtitle2_6": 32,
    "Title_1": 14,
    "Title3": 25,
    "txtSearch": 9
  },
  "ResourcesJsonIndices": {
    "Image-SampleImage": 0
  },
  "RuleScreenIdWithoutScreen": {},
  "TemplateVersions": {},
  "VolatileProperties": {
    "AnalysisLoadTime": 0.407443,
    "ControlCount": {
      "button": 3,
      "customControl": 8,
      "dataGrid": 1,
      "dropdown": 2,
      "gallery": 1,
      "galleryTemplate": 1,
      "group": 1,
      "groupContainer": 1,
      "icon": 2,
      "label": 12,
      "rectangle": 2,
      "screen": 1,
      "slider": 1,
      "text": 1
    },
    "DeserializationLoadTime": 3.0076877
  },
  "WasLocalDatabaseReferencesEmpty": true
}